setup.py
tls_client/__init__.py
tls_client/__version__.py
tls_client/cffi.py
tls_client/cookies.py
tls_client/exceptions.py
tls_client/response.py
tls_client/sessions.py
tls_client/settings.py
tls_client/structures.py
tls_session.egg-info/PKG-INFO
tls_session.egg-info/SOURCES.txt
tls_session.egg-info/dependency_links.txt
tls_session.egg-info/requires.txt
tls_session.egg-info/top_level.txt