Metadata-Version: 2.1
Name: tls-session
Version: 0.0.1
Summary: tls_session
Author: tls_session
